y2/__init__.py
y2/__main__.py
y2/_console.py
y2/_tempdirs.py
y2/_version.py
y2/clean.py
y2/hig.py
y2/xcode.py
y2-2025.3.dist-info/METADATA
y2-2025.3.dist-info/WHEEL
y2-2025.3.dist-info/entry_points.txt
y2-2025.3.dist-info/licenses/LICENSE
y2-2025.3.dist-info/RECORD
