Metadata-Version: 2.4
Name: y2
Version: 2025.3
Summary: Why have two when one will do?
Project-URL: Home, https://github.com/mangoumbrella/y2
Project-URL: Source, https://github.com/mangoumbrella/y2
Author-email: Mango Umbrella LLC <hi@mangoumbrella.com>
License-Expression: Apache-2.0
License-File: LICENSE
Keywords: CLI,Developer,Tool,Utility
Classifier: Development Status :: 4 - Beta
Classifier: Environment :: Console
Classifier: Intended Audience :: Developers
Classifier: Operating System :: OS Independent
Classifier: Programming Language :: Python
Classifier: Programming Language :: Python :: 3 :: Only
Classifier: Programming Language :: Python :: 3.13
Classifier: Topic :: Utilities
Requires-Python: >=3.13
Requires-Dist: beautifulsoup4>=4.13.4
Requires-Dist: cyclopts>=3.19.0
Requires-Dist: selenium>=4.33.0
